[
    {
        "name": "Flickerwisp",
        "image": "Image"
    },
    {
        "name": "Ainok Bond-Kin",
        "image": "Image (1)"
    },
    {
        "name": "Emrakul. the Aeons Torn",
        "image": "Image (2)"
    },
    {
        "name": "Kozilek. Butcher of Truth",
        "image": "Image (3)"
    },
    {
        "name": "Ulamos, the Infinite Gyre",
        "image": "Image (4)"
    },
    {
        "name": "Abzan Falconer",
        "image": "Image (5)"
    },
    {
        "name": "Anointer of Valor",
        "image": "Image (6)"
    },
    {
        "name": "Battlefield Promotion",
        "image": "Image (7)"
    },
    {
        "name": "Divine Visitation",
        "image": "Image (8)"
    },
    {
        "name": "Doomed Traveler",
        "image": "Image (9)"
    },
    {
        "name": "Gods Willing",
        "image": "Image (10)"
    },
    {
        "name": "Emiel the Blessed",
        "image": "Image (11)"
    }
]
 
 
